PyRandomNameGenerator/__init__.py
PyRandomNameGenerator-0.2.dist-info/LICENSE.txt
PyRandomNameGenerator-0.2.dist-info/METADATA
PyRandomNameGenerator-0.2.dist-info/WHEEL
PyRandomNameGenerator-0.2.dist-info/top_level.txt
PyRandomNameGenerator-0.2.dist-info/RECORD
