Metadata-Version: 2.1
Name: PyRandomNameGenerator
Version: 0.2
Summary: This is a simple name generator package
Home-page: https://pypi.org/project/PyRandomNameGenerator/
Author: Md. Ismiel Hossen Abir
License: MIT
License-File: LICENSE.txt
